pigframe/__init__.py
pigframe/_version.py
pigframe/action.py
pigframe/scene.py
pigframe/world.py
pigframe/examples/README.md
pigframe/examples/pygame_control_a_ball/README.md
pigframe/examples/pygame_control_a_ball/app.py
pigframe/examples/pygame_control_a_ball/component.py
pigframe/examples/pygame_control_a_ball/entity.py
pigframe/examples/pygame_control_a_ball/event.py
pigframe/examples/pygame_control_a_ball/screen.py
pigframe/examples/pygame_control_a_ball/system.py
pigframe/examples/pyxel_2d_shooting/README.md
pigframe/examples/pyxel_2d_shooting/actions.py
pigframe/examples/pyxel_2d_shooting/app.py
pigframe/examples/pyxel_2d_shooting/component.py
pigframe/examples/pyxel_2d_shooting/entity.py
pigframe/examples/pyxel_2d_shooting/event.py
pigframe/examples/pyxel_2d_shooting/screen.py
pigframe/examples/pyxel_2d_shooting/system.py
pigframe/examples/pyxel_control_a_ball/README.md
pigframe/examples/pyxel_control_a_ball/actions.py
pigframe/examples/pyxel_control_a_ball/app.py
pigframe/examples/pyxel_control_a_ball/component.py
pigframe/examples/pyxel_control_a_ball/entity.py
pigframe/examples/pyxel_control_a_ball/event.py
pigframe/examples/pyxel_control_a_ball/screen.py
pigframe/examples/pyxel_control_a_ball/system.py
pigframe/tests/test_component.py
pigframe/tests/test_level.py
pigframe/tests/test_world.py
pigframe-0.2.1.dist-info/LICENSE
pigframe-0.2.1.dist-info/METADATA
pigframe-0.2.1.dist-info/WHEEL
pigframe-0.2.1.dist-info/top_level.txt
pigframe-0.2.1.dist-info/RECORD
