Metadata-Version: 2.1
Name: pigframe
Version: 0.2.1
Summary: A minimum ECS (Entity Component System) library in Python, designed to simplify and streamline the development process of game application.
Home-page: https://github.com/passive-radio/pigframe
Author: passive-radio, Yudai Okubo
Author-email: srccreator@gmail.com
License: MIT
Project-URL: Documentation, https://github.com/passive-radio/pigframe
Project-URL: Source, https://github.com/passive-radio/pigframe
Keywords: python,game,framework
Classifier: Development Status :: 3 - Alpha
Classifier: License :: OSI Approved :: MIT License
Classifier: Programming Language :: Python :: 3
Classifier: Intended Audience :: Developers
Classifier: Topic :: Software Development :: Libraries :: Python Modules
Requires-Python: >=3.10
License-File: LICENSE
